etempmail/TempMail.py
etempmail/TempMailException.py
etempmail/__init__.py
etempmail-4.0.0.0.dist-info/LICENSE
etempmail-4.0.0.0.dist-info/METADATA
etempmail-4.0.0.0.dist-info/WHEEL
etempmail-4.0.0.0.dist-info/top_level.txt
etempmail-4.0.0.0.dist-info/RECORD
