Metadata-Version: 2.1
Name: etempmail
Version: 4.0.0.0
Summary: A simple module to get free disposable temporary email address
Home-page: https://github.com/mahelbir/etempmail
Author: Mahmuthan Elbir
Author-email: me@mahmuthanelbir.com.tr
License: MIT
Keywords: temp mail,temporary mail,disposable mail,temp email,etempmail,etempmail.com
Classifier: Programming Language :: Python :: 3
Classifier: License :: OSI Approved :: MIT License
Classifier: Operating System :: OS Independent
Requires-Python: >=3.7
License-File: LICENSE
Requires-Dist: requests ~=2.28.2
